{
  "success": true,
  "rebalance_date": "2025-06-12T22:26:54.702802",
  "new_portfolio": [
    "DIVISLAB.NS",
    "ICICIBANK.NS",
    "BHARTIARTL.NS",
    "BAJFINANCE.NS",
    "HDFCLIFE.NS",
    "HDFCBANK.NS",
    "KOTAKBANK.NS",
    "BAJAJFINSV.NS",
    "TECHM.NS",
    "SBILIFE.NS",
    "DRREDDY.NS",
    "APOLLOHOSP.NS",
    "MARICO.NS",
    "GRASIM.NS",
    "EICHERMOT.NS",
    "JSWSTEEL.NS",
    "BRITANNIA.NS",
    "AXISBANK.NS",
    "ADANIPORTS.NS",
    "MARUTI.NS",
    "LT.NS",
    "PIDILITIND.NS",
    "RELIANCE.NS",
    "SBIN.NS",
    "TITAN.NS",
    "NESTLEIND.NS",
    "LICI.NS",
    "TATASTEEL.NS",
    "DMART.NS"
  ],
  "previous_portfolio": [],
  "added_stocks": [
    "BRITANNIA.NS",
    "NESTLEIND.NS",
    "MARUTI.NS",
    "BHARTIARTL.NS",
    "HDFCBANK.NS",
    "DIVISLAB.NS",
    "KOTAKBANK.NS",
    "AXISBANK.NS",
    "EICHERMOT.NS",
    "SBIN.NS",
    "LT.NS",
    "BAJFINANCE.NS",
    "BAJAJFINSV.NS",
    "TATASTEEL.NS",
    "DMART.NS",
    "JSWSTEEL.NS",
    "ADANIPORTS.NS",
    "APOLLOHOSP.NS",
    "GRASIM.NS",
    "TECHM.NS",
    "DRREDDY.NS",
    "RELIANCE.NS",
    "SBILIFE.NS",
    "PIDILITIND.NS",
    "ICICIBANK.NS",
    "MARICO.NS",
    "TITAN.NS",
    "HDFCLIFE.NS",
    "LICI.NS"
  ],
  "removed_stocks": [],
  "screening_results": [
    {
      "ticker": "DIVISLAB.NS",
      "current_price": 6725.0,
      "dma_200": 5851.509504394531,
      "high_distance": 2.0036429872495445,
      "primary_sharpe": 1.6907731300766466,
      "sharpe_3m": 3.0092773091357228,
      "sharpe_6m": 1.0358612552419506,
      "sharpe_9m": 1.0747714636010852,
      "sharpe_12m": 1.6907731300766466,
      "sharpe_rank": 1.0
    },
    {
      "ticker": "ICICIBANK.NS",
      "current_price": 1425.199951171875,
      "dma_200": 1302.883248901367,
      "high_distance": 3.153032426192295,
      "primary_sharpe": 1.474184621282299,
      "sharpe_3m": 2.6753603840909315,
      "sharpe_6m": 0.6264196120077004,
      "sharpe_9m": 0.8925843547830368,
      "sharpe_12m": 1.474184621282299,
      "sharpe_rank": 2.0
    },
    {
      "ticker": "BHARTIARTL.NS",
      "current_price": 1844.199951171875,
      "dma_200": 1679.4652502441406,
      "high_distance": 3.797602964430099,
      "primary_sharpe": 1.3311809673441461,
      "sharpe_3m": 2.6569954894888017,
      "sharpe_6m": 1.0264582596041514,
      "sharpe_9m": 0.7763508567009167,
      "sharpe_12m": 1.3311809673441461,
      "sharpe_rank": 3.0
    },
    {
      "ticker": "BAJFINANCE.NS",
      "current_price": 9368.5,
      "dma_200": 7824.18466796875,
      "high_distance": 4.285860237024928,
      "primary_sharpe": 1.1355944906997053,
      "sharpe_3m": 1.629616207928085,
      "sharpe_6m": 2.524753789274442,
      "sharpe_9m": 1.4613098097908155,
      "sharpe_12m": 1.1355944906997053,
      "sharpe_rank": 4.0
    },
    {
      "ticker": "HDFCLIFE.NS",
      "current_price": 754.5,
      "dma_200": 684.0897512817382,
      "high_distance": 4.626466529572233,
      "primary_sharpe": 1.0756588966839975,
      "sharpe_3m": 4.372409554457376,
      "sharpe_6m": 1.7254780596371497,
      "sharpe_9m": 0.4341602462473507,
      "sharpe_12m": 1.0756588966839975,
      "sharpe_rank": 5.0
    },
    {
      "ticker": "HDFCBANK.NS",
      "current_price": 1943.4000244140625,
      "dma_200": 1767.4702490234374,
      "high_distance": 2.6499034774414825,
      "primary_sharpe": 1.065351022272471,
      "sharpe_3m": 3.2289468971852813,
      "sharpe_6m": 0.44656349962775055,
      "sharpe_9m": 1.1445171633315077,
      "sharpe_12m": 1.065351022272471,
      "sharpe_rank": 6.0
    },
    {
      "ticker": "KOTAKBANK.NS",
      "current_price": 2126.800048828125,
      "dma_200": 1914.5637481689453,
      "high_distance": 7.606753592427791,
      "primary_sharpe": 1.0476098819452289,
      "sharpe_3m": 1.195812035732432,
      "sharpe_6m": 1.5001867054991438,
      "sharpe_9m": 0.9097776675785149,
      "sharpe_12m": 1.0476098819452289,
      "sharpe_rank": 7.0
    },
    {
      "ticker": "BAJAJFINSV.NS",
      "current_price": 2028.800048828125,
      "dma_200": 1825.537999267578,
      "high_distance": 4.974236588846604,
      "primary_sharpe": 1.045608668817258,
      "sharpe_3m": 1.2960045030177674,
      "sharpe_6m": 1.5832488621875647,
      "sharpe_9m": 0.4563060721490165,
      "sharpe_12m": 1.045608668817258,
      "sharpe_rank": 8.0
    },
    {
      "ticker": "TECHM.NS",
      "current_price": 1644.4000244140625,
      "dma_200": 1605.882138671875,
      "high_distance": 9.03357477284603,
      "primary_sharpe": 0.8784809728661487,
      "sharpe_3m": 2.339559442432383,
      "sharpe_6m": -0.49176716317017427,
      "sharpe_9m": 0.029822278018755435,
      "sharpe_12m": 0.8784809728661487,
      "sharpe_rank": 9.0
    },
    {
      "ticker": "SBILIFE.NS",
      "current_price": 1766.0,
      "dma_200": 1604.82486328125,
      "high_distance": 8.607374970828886,
      "primary_sharpe": 0.8141490483098993,
      "sharpe_3m": 5.146936795132926,
      "sharpe_6m": 2.3055156662018352,
      "sharpe_9m": -0.15467006262560445,
      "sharpe_12m": 0.8141490483098993,
      "sharpe_rank": 10.0
    },
    {
      "ticker": "DRREDDY.NS",
      "current_price": 1362.699951171875,
      "dma_200": 1253.1514465332032,
      "high_distance": 4.135803942791514,
      "primary_sharpe": 0.6906073029937966,
      "sharpe_3m": 4.318700709980245,
      "sharpe_6m": 0.6451135167736216,
      "sharpe_9m": 0.15378614322488615,
      "sharpe_12m": 0.6906073029937966,
      "sharpe_rank": 11.0
    },
    {
      "ticker": "APOLLOHOSP.NS",
      "current_price": 6996.5,
      "dma_200": 6875.156069335938,
      "high_distance": 7.142869329203966,
      "primary_sharpe": 0.5790927166624069,
      "sharpe_3m": 3.3114078815013985,
      "sharpe_6m": -0.3164126279024789,
      "sharpe_9m": -0.02097761934600986,
      "sharpe_12m": 0.5790927166624069,
      "sharpe_rank": 12.0
    },
    {
      "ticker": "MARICO.NS",
      "current_price": 692.4500122070312,
      "dma_200": 660.289447631836,
      "high_distance": 6.450959093829967,
      "primary_sharpe": 0.4725428837222789,
      "sharpe_3m": 3.1124209319690084,
      "sharpe_6m": 0.7334612129575679,
      "sharpe_9m": 0.007638099206643778,
      "sharpe_12m": 0.4725428837222789,
      "sharpe_rank": 13.0
    },
    {
      "ticker": "GRASIM.NS",
      "current_price": 2689.10009765625,
      "dma_200": 2594.257492675781,
      "high_distance": 6.19637283350658,
      "primary_sharpe": 0.4111308791163941,
      "sharpe_3m": 2.2021166100465157,
      "sharpe_6m": 0.011813608501445524,
      "sharpe_9m": -0.1520309564217418,
      "sharpe_12m": 0.4111308791163941,
      "sharpe_rank": 14.0
    },
    {
      "ticker": "EICHERMOT.NS",
      "current_price": 5315.5,
      "dma_200": 5060.895502929688,
      "high_distance": 10.0059256751037,
      "primary_sharpe": 0.34261512608290867,
      "sharpe_3m": 0.984676280315122,
      "sharpe_6m": 0.7392999131916708,
      "sharpe_9m": 0.42009282339897125,
      "sharpe_12m": 0.34261512608290867,
      "sharpe_rank": 15.0
    },
    {
      "ticker": "JSWSTEEL.NS",
      "current_price": 995.6500244140625,
      "dma_200": 975.5774987792969,
      "high_distance": 7.372778695693107,
      "primary_sharpe": 0.320308836771248,
      "sharpe_3m": -0.1147709411333466,
      "sharpe_6m": 0.038066918629860884,
      "sharpe_9m": 0.1271626679800889,
      "sharpe_12m": 0.320308836771248,
      "sharpe_rank": 16.0
    },
    {
      "ticker": "BRITANNIA.NS",
      "current_price": 5569.5,
      "dma_200": 5303.765483398438,
      "high_distance": 13.916751664389368,
      "primary_sharpe": 0.22217232030761253,
      "sharpe_3m": 5.201820450641814,
      "sharpe_6m": 1.6904163889822994,
      "sharpe_9m": -0.48978091922932976,
      "sharpe_12m": 0.22217232030761253,
      "sharpe_rank": 17.0
    },
    {
      "ticker": "AXISBANK.NS",
      "current_price": 1212.9000244140625,
      "dma_200": 1124.1352505493164,
      "high_distance": 9.461426319567162,
      "primary_sharpe": 0.0790294632377524,
      "sharpe_3m": 3.2731200575404906,
      "sharpe_6m": 0.4547166642986422,
      "sharpe_9m": -0.08123597414277225,
      "sharpe_12m": 0.0790294632377524,
      "sharpe_rank": 18.0
    },
    {
      "ticker": "ADANIPORTS.NS",
      "current_price": 1445.800048828125,
      "dma_200": 1272.6099981689454,
      "high_distance": 9.916190983248084,
      "primary_sharpe": 0.0016810935561449357,
      "sharpe_3m": 5.256062168598024,
      "sharpe_6m": 1.1286892208495507,
      "sharpe_9m": 0.013260385168509399,
      "sharpe_12m": 0.0016810935561449357,
      "sharpe_rank": 19.0
    },
    {
      "ticker": "MARUTI.NS",
      "current_price": 12390.0,
      "dma_200": 11974.205478515625,
      "high_distance": 8.574359144776881,
      "primary_sharpe": -0.019253120644331448,
      "sharpe_3m": 1.579005650925132,
      "sharpe_6m": 0.9397522079128365,
      "sharpe_9m": 0.0491455118255947,
      "sharpe_12m": -0.019253120644331448,
      "sharpe_rank": 20.0
    },
    {
      "ticker": "LT.NS",
      "current_price": 3603.89990234375,
      "dma_200": 3483.7835498046875,
      "high_distance": 8.224774943268997,
      "primary_sharpe": -0.024646236705654894,
      "sharpe_3m": 2.5246077303035475,
      "sharpe_6m": -0.44919001758463106,
      "sharpe_9m": -0.03392036358350429,
      "sharpe_12m": -0.024646236705654894,
      "sharpe_rank": 21.0
    },
    {
      "ticker": "PIDILITIND.NS",
      "current_price": 3046.89990234375,
      "dma_200": 3009.460001220703,
      "high_distance": 10.778919404282577,
      "primary_sharpe": -0.100294474083778,
      "sharpe_3m": 2.8803374293599764,
      "sharpe_6m": -0.4411488476937917,
      "sharpe_9m": -0.5154352528167504,
      "sharpe_12m": -0.100294474083778,
      "sharpe_rank": 22.0
    },
    {
      "ticker": "RELIANCE.NS",
      "current_price": 1441.5999755859375,
      "dma_200": 1325.759125366211,
      "high_distance": 10.088719008589086,
      "primary_sharpe": -0.1070301535096995,
      "sharpe_3m": 3.3965570505263196,
      "sharpe_6m": 1.2727049379973294,
      "sharpe_9m": -0.11986498543250919,
      "sharpe_12m": -0.1070301535096995,
      "sharpe_rank": 23.0
    },
    {
      "ticker": "SBIN.NS",
      "current_price": 805.9500122070312,
      "dma_200": 774.5859802246093,
      "high_distance": 8.550264567658077,
      "primary_sharpe": -0.11874042867055275,
      "sharpe_3m": 2.8835997319440456,
      "sharpe_6m": -0.4006521523562436,
      "sharpe_9m": 0.27077572538536165,
      "sharpe_12m": -0.11874042867055275,
      "sharpe_rank": 24.0
    },
    {
      "ticker": "TITAN.NS",
      "current_price": 3452.699951171875,
      "dma_200": 3387.3020007324217,
      "high_distance": 10.713732837551719,
      "primary_sharpe": -0.15094692923325356,
      "sharpe_3m": 3.1289819396389262,
      "sharpe_6m": 0.03699281420819211,
      "sharpe_9m": -0.45180255911306416,
      "sharpe_12m": -0.15094692923325356,
      "sharpe_rank": 25.0
    },
    {
      "ticker": "NESTLEIND.NS",
      "current_price": 2385.60009765625,
      "dma_200": 2322.1440747070315,
      "high_distance": 13.575336805871316,
      "primary_sharpe": -0.30217859312835726,
      "sharpe_3m": 2.550632382464613,
      "sharpe_6m": 0.7841169032128646,
      "sharpe_9m": -0.3975406373420002,
      "sharpe_12m": -0.30217859312835726,
      "sharpe_rank": 26.0
    },
    {
      "ticker": "LICI.NS",
      "current_price": 943.7000122070312,
      "dma_200": 885.649504699707,
      "high_distance": 22.77413975392543,
      "primary_sharpe": -0.35995099375779777,
      "sharpe_3m": 5.196433557084204,
      "sharpe_6m": 0.15657359557940487,
      "sharpe_9m": -0.4034309606651544,
      "sharpe_12m": -0.35995099375779777,
      "sharpe_rank": 27.0
    },
    {
      "ticker": "TATASTEEL.NS",
      "current_price": 152.88999938964844,
      "dma_200": 143.26050811767578,
      "high_distance": 13.5386216356077,
      "primary_sharpe": -0.4135282793909286,
      "sharpe_3m": 0.35135406290710053,
      "sharpe_6m": 0.3711491145679513,
      "sharpe_9m": 0.065106015589134,
      "sharpe_12m": -0.4135282793909286,
      "sharpe_rank": 28.0
    },
    {
      "ticker": "DMART.NS",
      "current_price": 4074.0,
      "dma_200": 4070.9844946289063,
      "high_distance": 25.72267377478785,
      "primary_sharpe": -0.6304126124381662,
      "sharpe_3m": 1.1612613435229255,
      "sharpe_6m": 0.800373808634376,
      "sharpe_9m": -0.854186336063117,
      "sharpe_12m": -0.6304126124381662,
      "sharpe_rank": 29.0
    }
  ]
}